{
  "@context": {
    "ldp": "http://www.w3.org/ns/ldp#",
    "schema": "http://schema.org/",
    "fedora": "http://fedora.info/definitions/v4/repository#",
    "webac": "http://fedora.info/definitions/v4/webac#",
    "acl": "http://www.w3.org/ns/auth/acl#",
    "ucdlib": "http://digital.ucdavis.edu/schema#",
    "ebucore": "http://www.ebu.ch/metadata/ontologies/ebucore/ebucore#"
  },
  "@id": "",
  "@type": [
    "schema:VisualArtwork",
    "schema:CreativeWork",
    "schema:ImageObject",
    "http://fedora.info/definitions/v4/repository#ArchivalGroup"
  ],
  "schema:about": {
    "@id": "http://id.worldcat.org/fast/1984649"
  },
  "schema:associatedMedia": {
    "@id": "@base:/d36c1g.jpg"
  },
  "schema:creator": "Curry, Ezra, Ethan, Emily, Angela, and Sean",
  "schema:datePublished": {
    "@type": "http://www.w3.org/2001/XMLSchema#gYear",
    "@value": "2020"
  },
  "schema:description": "__Artist's Statement:__ This is our painting project with the kids. The back ground is made from 16 A4 sized black construction paper taped together in order to make a large enough art area. The kids painted with their hands and feet dipped in paint. The first layer was one with predominantly cold colours. The kids dipped their feet in paint and walked around. Then we cut out stencils representing our family & home. The second layer was done over stencils with hands dipped in warm colours then stencils removed.  \n __Participant age:__ 4, 2, 1, 30, 30  \n __Category:__  Family Art (collaborative piece from members of same family)",
  "schema:identifier": [
    "ark:/87293/d36c1g",
    "D-693"
  ],
  "schema:isPartOf": {
    "@id": "https://oac.cdlib.org/findaid/ark:/13030/c86116mn/"
  },
  "schema:license": {
    "@id": "http://rightsstatements.org/vocab/InC-NC/1.0/"
  },
  "schema:name": "Our Family Sheltering At Home",
  "schema:publisher": [
    {
      "@id": "http://id.loc.gov/authorities/names/no2008108707"
    },
    "UC Davis Library, Archives and Special Collections"
  ],
  "schema:sdDatePublished": {
    "@type": "http://www.w3.org/2001/XMLSchema#gYear",
    "@value": "2021"
  },
  "schema:sdPublisher": [
    {
      "@id": "http://id.loc.gov/authorities/names/no2008108707"
    },
    "UC Davis, Archives and Special Collections"
  ]
}